Workbook
Name aporte: Sheet1!$F$19
Name patrimonio: Sheet1!$F$22
Name qtd_anos: Sheet1!$F$20
Name rendimento_carteira: Sheet1!$F$15
Name taxa_mensal: Sheet1!$F$21

Sheet Sheet1
D13: CONFIGURAÇÕES
D14: Salário | F14: 2000
D15: Rendimento Carteira | F15: 0.01
D16: Seguestão de Investimento (30%) | F16: =F14*0.3 -> 600
D18: INVESTIMENTO MENSAL
D19: Quanto investir por mês? | F19: =F16 -> 600
D20: Por quantos anos? | F20: 5
D21: Taxa de Rendimento Mensal? | F21: 0.0108
D22: Patrimônio acumulado? | F22: =FV(taxa_mensal,qtd_anos*12,aporte*-1) -> 50282.412
D23: Dividendos Mensais? | F23: =patrimonio*rendimento_carteira -> 502.82412
D25: CENÁRIOS | F25: DIVIDENDO
A26: 2 | D26: Valor em 2 anos? | E26: =FV($F$21,A26*12,$F$19*-1) -> 16338.518 | F26: =E26*rendimento_carteira -> 163.38518
A27: 5 | D27: Valor em 5 anos? | E27: =FV($F$21,A27*12,$F$19*-1) -> 50282.412 | F27: =E27*rendimento_carteira -> 502.82412
A28: 10 | D28: Valor em 10 anos? | E28: =FV($F$21,A28*12,$F$19*-1) -> 146074.6 | F28: =E28*rendimento_carteira -> 1460.746
A29: 20 | D29: Valor em 20 anos? | E29: =FV($F$21,A29*12,$F$19*-1) -> 676229.4 | F29: =E29*rendimento_carteira -> 6762.294
A30: 30 | D30: Valor em 30 anos? | E30: =FV($F$21,A30*12,$F$19*-1) -> 2600342.9 | F30: =E30*rendimento_carteira -> 26003.429
D34: PERFIL | E34: MODERADO
D35: VALOR A SER INVESTIDO POR MÊS | E35: 500
D37: TIPO DE FII | E37: PERCENTUAL SUGERIDO | F37: VALORES
D38: PAPEL | E38: =VLOOKUP($E$34&"-"&D38,Sheet2!A:D,4,FALSE) -> 0.32 | F38: =E38*$E$35 -> 160
D39: TIJOLO | E39: =VLOOKUP($E$34&"-"&D39,Sheet2!A:D,4,FALSE) -> 0.35 | F39: =E39*$E$35 -> 175
D40: HÍBRIDOS | E40: =VLOOKUP($E$34&"-"&D40,Sheet2!A:D,4,FALSE) -> 0.08 | F40: =E40*$E$35 -> 40
D41: FOFs | E41: =VLOOKUP($E$34&"-"&D41,Sheet2!A:D,4,FALSE) -> 0.05 | F41: =E41*$E$35 -> 25
D42: DESENVOLVIMENTO | E42: =VLOOKUP($E$34&"-"&D42,Sheet2!A:D,4,FALSE) -> 0.1 | F42: =E42*$E$35 -> 50
D43: HOTELARIAS | E43: =VLOOKUP($E$34&"-"&D43,Sheet2!A:D,4,FALSE) -> 0.1 | F43: =E43*$E$35 -> 50
F44: =SUM(F38:F43) -> 500

Sheet Sheet2
A3: CHAVE | B3: PERFIL | C3: TIPO DE FII | D3: %
A4: =B4&"-"&C4 -> CONSERVADOR-PAPEL | B4: CONSERVADOR | C4: PAPEL | D4: 0.3
A5: =B5&"-"&C5 -> CONSERVADOR-TIJOLO | B5: CONSERVADOR | C5: TIJOLO | D5: 0.5
A6: =B6&"-"&C6 -> CONSERVADOR-HÍBRIDOS | B6: CONSERVADOR | C6: HÍBRIDOS | D6: 0.1
A7: =B7&"-"&C7 -> CONSERVADOR-FOFs | B7: CONSERVADOR | C7: FOFs | D7: 0.1
A8: =B8&"-"&C8 -> CONSERVADOR-DESENVOLVIMENTO | B8: CONSERVADOR | C8: DESENVOLVIMENTO | D8: 0
A9: =B9&"-"&C9 -> CONSERVADOR-HOTELARIAS | B9: CONSERVADOR | C9: HOTELARIAS | D9: 0
A10: =B10&"-"&C10 -> MODERADO-PAPEL | B10: MODERADO | C10: PAPEL | D10: 0.32
A11: =B11&"-"&C11 -> MODERADO-TIJOLO | B11: MODERADO | C11: TIJOLO | D11: 0.35
A12: =B12&"-"&C12 -> MODERADO-HÍBRIDOS | B12: MODERADO | C12: HÍBRIDOS | D12: 0.08
A13: =B13&"-"&C13 -> MODERADO-FOFs | B13: MODERADO | C13: FOFs | D13: 0.05
A14: =B14&"-"&C14 -> MODERADO-DESENVOLVIMENTO | B14: MODERADO | C14: DESENVOLVIMENTO | D14: 0.1
A15: =B15&"-"&C15 -> MODERADO-HOTELARIAS | B15: MODERADO | C15: HOTELARIAS | D15: 0.1
... A21: =B21&"-"&C21 -> AGRESSIVO-HOTELARIAS | B21: AGRESSIVO | C21: HOTELARIAS | D21: 0.1
